{
  "name": "RótulosImperdíveis",
  "path": "/rotulosimperdiveis",
  "sections": [
    {
      "__resolveType": "website/sections/Rendering/Lazy.tsx",
      "section": {
        "__resolveType": "Header"
      }
    },
    {
      "__resolveType": "website/sections/Rendering/Lazy.tsx",
      "section": {
        "__resolveType": "site/sections/Images/ImageGallery.tsx",
        "banners": [
          {
            "positionBanner": "Full",
            "region": "Mostrar em ambas",
            "initialDate": "0",
            "deadLine": "0",
            "mobile": "https://assets.decocache.com/festval/f5a7f72f-fd41-4659-96ac-98a78e83b662/WPPJHONNYBANNER-MBL.jpg",
            "desktop": "https://assets.decocache.com/festval/793d1060-98c9-4597-a0f8-99ad402b4056/WPPJHONNYBANNER.jpg",
            "alt": "wppjhonny",
            "href": "https://api.whatsapp.com/send/?phone=554187731596&text=Ol%C3%A1%2C+vim+do+Festval.com+e+gostaria+de+saber+mais+sobre+a+adega+Festval.&type=phone_number&app_absent=0&utm_source=Bannerlp&utm_campaign=WppSommelier",
            "hrefMobile": "https://api.whatsapp.com/send/?phone=554187731596&text=Ol%C3%A1%2C+vim+do+Festval.com+e+gostaria+de+saber+mais+sobre+a+adega+Festval.&type=phone_number&app_absent=0&utm_source=Bannerlp&utm_campaign=WppSommelier",
            "activeTerm": false
          }
        ]
      }
    },
    {
      "__resolveType": "website/sections/Rendering/Lazy.tsx",
      "section": {
        "__resolveType": "site/sections/Product/SearchResult.tsx",
        "page": {
          "__resolveType": "vtex/loaders/intelligentSearch/productListingPage.ts",
          "count": 12,
          "sort": "",
          "fuzzy": "automatic",
          "selectedFacets": [
            {
              "value": "1627",
              "key": "productClusterIds"
            }
          ]
        }
      }
    },
    {
      "__resolveType": "website/sections/Rendering/Lazy.tsx",
      "section": {
        "__resolveType": "Footer"
      }
    }
  ],
  "seo": {
    "__resolveType": "website/sections/Seo/SeoV2.tsx"
  },
  "__resolveType": "website/pages/Page.tsx"
}